[
	{
		"count": 93568,
		"name": "list-scroll-fix",
		"version": "all"
	},
	{
		"count": 69306,
		"name": "RoundCornerNCM",
		"version": "all"
	},
	{
		"count": 4323,
		"name": "search-this-singer",
		"version": "all"
	},
	{
		"count": 4196,
		"name": "keyboard-seek",
		"version": "all"
	},
	{
		"count": 21401,
		"name": "crossfade-lfp",
		"version": "all"
	},
	{
		"count": 5661,
		"name": "Apple-Musiclike-lyrics-2-0-Beta",
		"version": "all"
	},
	{
		"count": 0,
		"name": "PluginMarket",
		"version": "all"
	},
	{
		"count": 74677,
		"name": "BGEnhanced",
		"version": "all"
	},
	{
		"count": 23522,
		"name": "SimpleAudioVisualizer",
		"version": "all"
	},
	{
		"count": 9598,
		"name": "play-with-bilibili",
		"version": "all"
	},
	{
		"count": 28646,
		"name": "libsonginfo",
		"version": "all"
	},
	{
		"count": 4841,
		"name": "CrashFix",
		"version": "all"
	},
	{
		"count": 55774,
		"name": "FluentProgressBar",
		"version": "all"
	},
	{
		"count": 24070,
		"name": "elaina-theme",
		"version": "all"
	},
	{
		"count": 43503,
		"name": "LibFrontendPlay",
		"version": "all"
	},
	{
		"count": 2942,
		"name": "RevivedUnblockInstaller",
		"version": "all"
	},
	{
		"count": 26103,
		"name": "RuLyrics",
		"version": "all"
	},
	{
		"count": 15174,
		"name": "Transmission",
		"version": "all"
	},
	{
		"count": 19035,
		"name": "ActionEnhancement",
		"version": "all"
	},
	{
		"count": 19943,
		"name": "ark-theme",
		"version": "all"
	},
	{
		"count": 68856,
		"name": "LibEAPIRequest",
		"version": "all"
	},
	{
		"count": 24166,
		"name": "VisualRecord",
		"version": "all"
	},
	{
		"count": 110917,
		"name": "RefinedNowPlaying",
		"version": "all"
	},
	{
		"count": 3986,
		"name": "search-on-osu",
		"version": "all"
	},
	{
		"count": 12059,
		"name": "FluentMusicCover",
		"version": "all"
	},
	{
		"count": 45747,
		"name": "StyleSnippet",
		"version": "all"
	},
	{
		"count": 0,
		"name": "MoreHooks",
		"version": "all"
	},
	{
		"count": 51504,
		"name": "Taskbar-Lyrics",
		"version": "all"
	},
	{
		"count": 25756,
		"name": "What-is-the-cover-of-this-music",
		"version": "all"
	},
	{
		"count": 67708,
		"name": "liblyric",
		"version": "all"
	},
	{
		"count": 178621,
		"name": "InfLink",
		"version": "all"
	},
	{
		"count": 88065,
		"name": "MaterialYouTheme",
		"version": "all"
	},
	{
		"count": 60454,
		"name": "light-dark-theme-switcher",
		"version": "all"
	},
	{
		"count": 72229,
		"name": "MoTheme",
		"version": "all"
	},
	{
		"count": 12459,
		"name": "Unbounded",
		"version": "all"
	},
	{
		"count": 5223,
		"name": "HideScrollbar",
		"version": "all"
	},
	{
		"count": 30876,
		"name": "TinyNCM",
		"version": "all"
	},
	{
		"count": 3966,
		"name": "Customize",
		"version": "all"
	},
	{
		"count": 5003,
		"name": "remove-tracking-attribute",
		"version": "all"
	},
	{
		"count": 0,
		"name": "UnblockCloudMusicInstaller",
		"version": "all"
	},
	{
		"count": 4347,
		"name": "PlaybackRate",
		"version": "all"
	},
	{
		"count": 9950,
		"name": "GPTTrans",
		"version": "all"
	},
	{
		"count": 17912,
		"name": "LyricBar",
		"version": "all"
	},
	{
		"count": 6609,
		"name": "relive-theme",
		"version": "all"
	},
	{
		"count": 24312,
		"name": "MikuPlugin",
		"version": "all"
	},
	{
		"count": 8194,
		"name": "RevivedSource",
		"version": "all"
	},
	{
		"count": 86046,
		"name": "StylesheetLoader",
		"version": "all"
	},
	{
		"count": 5387,
		"name": "LiveSongPlayer",
		"version": "all"
	},
	{
		"count": 4704,
		"name": "vocaloid-info",
		"version": "all"
	},
	{
		"count": 9480,
		"name": "Microrange",
		"version": "all"
	},
	{
		"count": 40759,
		"name": "Apple-Musiclike-lyrics",
		"version": "all"
	}
]