[
	{
		"count": 187717,
		"name": "StylesheetLoader",
		"version": "all"
	},
	{
		"count": 67135,
		"name": "Apple-Musiclike-lyrics",
		"version": "all"
	},
	{
		"count": 27432,
		"name": "libsonginfo",
		"version": "all"
	},
	{
		"count": 8971,
		"name": "DowngradeOK",
		"version": "all"
	},
	{
		"count": 51233,
		"name": "TinyNCM",
		"version": "all"
	},
	{
		"count": 18233,
		"name": "GPTTrans",
		"version": "all"
	},
	{
		"count": 233087,
		"name": "RefinedNowPlaying",
		"version": "all"
	},
	{
		"count": 45859,
		"name": "SimpleAudioVisualizer",
		"version": "all"
	},
	{
		"count": 18683,
		"name": "play-with-bilibili",
		"version": "all"
	},
	{
		"count": 5423,
		"name": "PiPWindow",
		"version": "all"
	},
	{
		"count": 42977,
		"name": "LyricBar",
		"version": "all"
	},
	{
		"count": 141057,
		"name": "LibEAPIRequest",
		"version": "all"
	},
	{
		"count": 104866,
		"name": "LibFrontendPlay",
		"version": "all"
	},
	{
		"count": 5516,
		"name": "vocaloid-info",
		"version": "all"
	},
	{
		"count": 66329,
		"name": "RuLyrics",
		"version": "all"
	},
	{
		"count": 2957,
		"name": "LyricBarBlur",
		"version": "all"
	},
	{
		"count": 193091,
		"name": "InfLink",
		"version": "all"
	},
	{
		"count": 30533,
		"name": "LogCleaner",
		"version": "all"
	},
	{
		"count": 1251,
		"name": "cpplyrics",
		"version": "all"
	},
	{
		"count": 92571,
		"name": "StyleSnippet",
		"version": "all"
	},
	{
		"count": 63664,
		"name": "Taskbar-Lyrics",
		"version": "all"
	},
	{
		"count": 0,
		"name": "MoreHooks",
		"version": "all"
	},
	{
		"count": 1647,
		"name": "artist-all-songs",
		"version": "all"
	},
	{
		"count": 166879,
		"name": "MoTheme",
		"version": "all"
	},
	{
		"count": 7042,
		"name": "Apple-Musiclike-lyrics-2-0-Beta",
		"version": "all"
	},
	{
		"count": 10758,
		"name": "keyboard-seek",
		"version": "all"
	},
	{
		"count": 118841,
		"name": "MaterialYouTheme",
		"version": "all"
	},
	{
		"count": 239962,
		"name": "list-scroll-fix",
		"version": "all"
	},
	{
		"count": 28833,
		"name": "elaina-theme",
		"version": "all"
	},
	{
		"count": 166876,
		"name": "RoundCornerNCM",
		"version": "all"
	},
	{
		"count": 7239,
		"name": "search-on-osu",
		"version": "all"
	},
	{
		"count": 133612,
		"name": "liblyric",
		"version": "all"
	},
	{
		"count": 22276,
		"name": "FluentMusicCover",
		"version": "all"
	},
	{
		"count": 7893,
		"name": "RevisedSecondaryWindows",
		"version": "all"
	},
	{
		"count": 1895,
		"name": "JapaneseFonts",
		"version": "all"
	},
	{
		"count": 25909,
		"name": "RevivedSource",
		"version": "all"
	},
	{
		"count": 3604,
		"name": "beat-saver",
		"version": "all"
	},
	{
		"count": 51838,
		"name": "VisualRecord",
		"version": "all"
	},
	{
		"count": 0,
		"name": "PluginMarket",
		"version": "all"
	},
	{
		"count": 8093,
		"name": "search-this-singer",
		"version": "all"
	},
	{
		"count": 168678,
		"name": "light-dark-theme-switcher",
		"version": "all"
	},
	{
		"count": 3495,
		"name": "ZoomNCM",
		"version": "all"
	},
	{
		"count": 9215,
		"name": "BGEnhanced-Extra",
		"version": "all"
	},
	{
		"count": 6986,
		"name": "Customize",
		"version": "all"
	},
	{
		"count": 47294,
		"name": "MikuPlugin",
		"version": "all"
	},
	{
		"count": 29830,
		"name": "Transmission",
		"version": "all"
	},
	{
		"count": 38506,
		"name": "ark-theme",
		"version": "all"
	},
	{
		"count": 24267,
		"name": "Unbounded",
		"version": "all"
	},
	{
		"count": 110166,
		"name": "FluentProgressBar",
		"version": "all"
	},
	{
		"count": 9704,
		"name": "PlaybackRate",
		"version": "all"
	},
	{
		"count": 9394,
		"name": "HideScrollbar",
		"version": "all"
	},
	{
		"count": 32574,
		"name": "ActionEnhancement",
		"version": "all"
	},
	{
		"count": 69318,
		"name": "crossfade-lfp",
		"version": "all"
	},
	{
		"count": 15122,
		"name": "CrashFix",
		"version": "all"
	},
	{
		"count": 19187,
		"name": "Microrange",
		"version": "all"
	},
	{
		"count": 8294,
		"name": "LiveSongPlayer",
		"version": "all"
	},
	{
		"count": 152031,
		"name": "BGEnhanced",
		"version": "all"
	},
	{
		"count": 14747,
		"name": "remove-tracking-attribute",
		"version": "all"
	},
	{
		"count": 12743,
		"name": "relive-theme",
		"version": "all"
	},
	{
		"count": 43028,
		"name": "What-is-the-cover-of-this-music",
		"version": "all"
	}
]