[
	{
		"count": 118912,
		"name": "list-scroll-fix",
		"version": "all"
	},
	{
		"count": 83119,
		"name": "RoundCornerNCM",
		"version": "all"
	},
	{
		"count": 5372,
		"name": "search-this-singer",
		"version": "all"
	},
	{
		"count": 5330,
		"name": "keyboard-seek",
		"version": "all"
	},
	{
		"count": 28889,
		"name": "crossfade-lfp",
		"version": "all"
	},
	{
		"count": 5661,
		"name": "Apple-Musiclike-lyrics-2-0-Beta",
		"version": "all"
	},
	{
		"count": 0,
		"name": "PluginMarket",
		"version": "all"
	},
	{
		"count": 89853,
		"name": "BGEnhanced",
		"version": "all"
	},
	{
		"count": 28193,
		"name": "SimpleAudioVisualizer",
		"version": "all"
	},
	{
		"count": 12237,
		"name": "play-with-bilibili",
		"version": "all"
	},
	{
		"count": 28689,
		"name": "libsonginfo",
		"version": "all"
	},
	{
		"count": 6284,
		"name": "CrashFix",
		"version": "all"
	},
	{
		"count": 66849,
		"name": "FluentProgressBar",
		"version": "all"
	},
	{
		"count": 30447,
		"name": "elaina-theme",
		"version": "all"
	},
	{
		"count": 53849,
		"name": "LibFrontendPlay",
		"version": "all"
	},
	{
		"count": 4831,
		"name": "RevivedUnblockInstaller",
		"version": "all"
	},
	{
		"count": 32927,
		"name": "RuLyrics",
		"version": "all"
	},
	{
		"count": 17616,
		"name": "Transmission",
		"version": "all"
	},
	{
		"count": 21831,
		"name": "ActionEnhancement",
		"version": "all"
	},
	{
		"count": 25237,
		"name": "ark-theme",
		"version": "all"
	},
	{
		"count": 81998,
		"name": "LibEAPIRequest",
		"version": "all"
	},
	{
		"count": 28858,
		"name": "VisualRecord",
		"version": "all"
	},
	{
		"count": 132247,
		"name": "RefinedNowPlaying",
		"version": "all"
	},
	{
		"count": 4776,
		"name": "search-on-osu",
		"version": "all"
	},
	{
		"count": 14625,
		"name": "FluentMusicCover",
		"version": "all"
	},
	{
		"count": 54189,
		"name": "StyleSnippet",
		"version": "all"
	},
	{
		"count": 0,
		"name": "MoreHooks",
		"version": "all"
	},
	{
		"count": 61663,
		"name": "Taskbar-Lyrics",
		"version": "all"
	},
	{
		"count": 29684,
		"name": "What-is-the-cover-of-this-music",
		"version": "all"
	},
	{
		"count": 80183,
		"name": "liblyric",
		"version": "all"
	},
	{
		"count": 207099,
		"name": "InfLink",
		"version": "all"
	},
	{
		"count": 104526,
		"name": "MaterialYouTheme",
		"version": "all"
	},
	{
		"count": 76859,
		"name": "light-dark-theme-switcher",
		"version": "all"
	},
	{
		"count": 86818,
		"name": "MoTheme",
		"version": "all"
	},
	{
		"count": 14681,
		"name": "Unbounded",
		"version": "all"
	},
	{
		"count": 5974,
		"name": "HideScrollbar",
		"version": "all"
	},
	{
		"count": 37264,
		"name": "TinyNCM",
		"version": "all"
	},
	{
		"count": 4680,
		"name": "Customize",
		"version": "all"
	},
	{
		"count": 7285,
		"name": "remove-tracking-attribute",
		"version": "all"
	},
	{
		"count": 0,
		"name": "UnblockCloudMusicInstaller",
		"version": "all"
	},
	{
		"count": 5584,
		"name": "PlaybackRate",
		"version": "all"
	},
	{
		"count": 12388,
		"name": "GPTTrans",
		"version": "all"
	},
	{
		"count": 22840,
		"name": "LyricBar",
		"version": "all"
	},
	{
		"count": 5143,
		"name": "BGEnhanced-Extra",
		"version": "all"
	},
	{
		"count": 8254,
		"name": "relive-theme",
		"version": "all"
	},
	{
		"count": 28214,
		"name": "MikuPlugin",
		"version": "all"
	},
	{
		"count": 11817,
		"name": "RevivedSource",
		"version": "all"
	},
	{
		"count": 102044,
		"name": "StylesheetLoader",
		"version": "all"
	},
	{
		"count": 6079,
		"name": "LiveSongPlayer",
		"version": "all"
	},
	{
		"count": 5931,
		"name": "vocaloid-info",
		"version": "all"
	},
	{
		"count": 11264,
		"name": "Microrange",
		"version": "all"
	},
	{
		"count": 48614,
		"name": "Apple-Musiclike-lyrics",
		"version": "all"
	}
]