[
	{
		"count": 157725,
		"name": "StylesheetLoader",
		"version": "all"
	},
	{
		"count": 59872,
		"name": "Apple-Musiclike-lyrics",
		"version": "all"
	},
	{
		"count": 27358,
		"name": "libsonginfo",
		"version": "all"
	},
	{
		"count": 44597,
		"name": "TinyNCM",
		"version": "all"
	},
	{
		"count": 16044,
		"name": "GPTTrans",
		"version": "all"
	},
	{
		"count": 179375,
		"name": "RefinedNowPlaying",
		"version": "all"
	},
	{
		"count": 40378,
		"name": "SimpleAudioVisualizer",
		"version": "all"
	},
	{
		"count": 16479,
		"name": "play-with-bilibili",
		"version": "all"
	},
	{
		"count": 34167,
		"name": "LyricBar",
		"version": "all"
	},
	{
		"count": 122629,
		"name": "LibEAPIRequest",
		"version": "all"
	},
	{
		"count": 88168,
		"name": "LibFrontendPlay",
		"version": "all"
	},
	{
		"count": 4350,
		"name": "vocaloid-info",
		"version": "all"
	},
	{
		"count": 56841,
		"name": "RuLyrics",
		"version": "all"
	},
	{
		"count": 173596,
		"name": "InfLink",
		"version": "all"
	},
	{
		"count": 20535,
		"name": "LogCleaner",
		"version": "all"
	},
	{
		"count": 80821,
		"name": "StyleSnippet",
		"version": "all"
	},
	{
		"count": 54343,
		"name": "Taskbar-Lyrics",
		"version": "all"
	},
	{
		"count": 0,
		"name": "MoreHooks",
		"version": "all"
	},
	{
		"count": 138112,
		"name": "MoTheme",
		"version": "all"
	},
	{
		"count": 8974,
		"name": "keyboard-seek",
		"version": "all"
	},
	{
		"count": 102192,
		"name": "MaterialYouTheme",
		"version": "all"
	},
	{
		"count": 202267,
		"name": "list-scroll-fix",
		"version": "all"
	},
	{
		"count": 23488,
		"name": "elaina-theme",
		"version": "all"
	},
	{
		"count": 144546,
		"name": "RoundCornerNCM",
		"version": "all"
	},
	{
		"count": 6585,
		"name": "search-on-osu",
		"version": "all"
	},
	{
		"count": 116673,
		"name": "liblyric",
		"version": "all"
	},
	{
		"count": 18273,
		"name": "FluentMusicCover",
		"version": "all"
	},
	{
		"count": 20686,
		"name": "RevivedSource",
		"version": "all"
	},
	{
		"count": 2676,
		"name": "beat-saver",
		"version": "all"
	},
	{
		"count": 44966,
		"name": "VisualRecord",
		"version": "all"
	},
	{
		"count": 0,
		"name": "PluginMarket",
		"version": "all"
	},
	{
		"count": 7165,
		"name": "search-this-singer",
		"version": "all"
	},
	{
		"count": 138263,
		"name": "light-dark-theme-switcher",
		"version": "all"
	},
	{
		"count": 6766,
		"name": "BGEnhanced-Extra",
		"version": "all"
	},
	{
		"count": 6391,
		"name": "Customize",
		"version": "all"
	},
	{
		"count": 41936,
		"name": "MikuPlugin",
		"version": "all"
	},
	{
		"count": 27227,
		"name": "Transmission",
		"version": "all"
	},
	{
		"count": 31479,
		"name": "ark-theme",
		"version": "all"
	},
	{
		"count": 22259,
		"name": "Unbounded",
		"version": "all"
	},
	{
		"count": 95179,
		"name": "FluentProgressBar",
		"version": "all"
	},
	{
		"count": 8223,
		"name": "PlaybackRate",
		"version": "all"
	},
	{
		"count": 8327,
		"name": "HideScrollbar",
		"version": "all"
	},
	{
		"count": 29818,
		"name": "ActionEnhancement",
		"version": "all"
	},
	{
		"count": 56252,
		"name": "crossfade-lfp",
		"version": "all"
	},
	{
		"count": 12231,
		"name": "CrashFix",
		"version": "all"
	},
	{
		"count": 17151,
		"name": "Microrange",
		"version": "all"
	},
	{
		"count": 7670,
		"name": "LiveSongPlayer",
		"version": "all"
	},
	{
		"count": 125730,
		"name": "BGEnhanced",
		"version": "all"
	},
	{
		"count": 12309,
		"name": "remove-tracking-attribute",
		"version": "all"
	},
	{
		"count": 10688,
		"name": "relive-theme",
		"version": "all"
	},
	{
		"count": 37192,
		"name": "What-is-the-cover-of-this-music",
		"version": "all"
	}
]