[
	{
		"count": 115605,
		"name": "StylesheetLoader",
		"version": "all"
	},
	{
		"count": 42358,
		"name": "Apple-Musiclike-lyrics",
		"version": "all"
	},
	{
		"count": 27252,
		"name": "libsonginfo",
		"version": "all"
	},
	{
		"count": 32392,
		"name": "TinyNCM",
		"version": "all"
	},
	{
		"count": 12076,
		"name": "GPTTrans",
		"version": "all"
	},
	{
		"count": 105084,
		"name": "RefinedNowPlaying",
		"version": "all"
	},
	{
		"count": 30586,
		"name": "SimpleAudioVisualizer",
		"version": "all"
	},
	{
		"count": 12182,
		"name": "play-with-bilibili",
		"version": "all"
	},
	{
		"count": 22560,
		"name": "LyricBar",
		"version": "all"
	},
	{
		"count": 94293,
		"name": "LibEAPIRequest",
		"version": "all"
	},
	{
		"count": 62558,
		"name": "LibFrontendPlay",
		"version": "all"
	},
	{
		"count": 2144,
		"name": "vocaloid-info",
		"version": "all"
	},
	{
		"count": 39462,
		"name": "RuLyrics",
		"version": "all"
	},
	{
		"count": 134288,
		"name": "InfLink",
		"version": "all"
	},
	{
		"count": 6938,
		"name": "LogCleaner",
		"version": "all"
	},
	{
		"count": 60459,
		"name": "StyleSnippet",
		"version": "all"
	},
	{
		"count": 37449,
		"name": "Taskbar-Lyrics",
		"version": "all"
	},
	{
		"count": 0,
		"name": "MoreHooks",
		"version": "all"
	},
	{
		"count": 99317,
		"name": "MoTheme",
		"version": "all"
	},
	{
		"count": 6179,
		"name": "keyboard-seek",
		"version": "all"
	},
	{
		"count": 73173,
		"name": "MaterialYouTheme",
		"version": "all"
	},
	{
		"count": 147133,
		"name": "list-scroll-fix",
		"version": "all"
	},
	{
		"count": 12881,
		"name": "elaina-theme",
		"version": "all"
	},
	{
		"count": 100062,
		"name": "RoundCornerNCM",
		"version": "all"
	},
	{
		"count": 5379,
		"name": "search-on-osu",
		"version": "all"
	},
	{
		"count": 90793,
		"name": "liblyric",
		"version": "all"
	},
	{
		"count": 12174,
		"name": "FluentMusicCover",
		"version": "all"
	},
	{
		"count": 13110,
		"name": "RevivedSource",
		"version": "all"
	},
	{
		"count": 956,
		"name": "beat-saver",
		"version": "all"
	},
	{
		"count": 33695,
		"name": "VisualRecord",
		"version": "all"
	},
	{
		"count": 0,
		"name": "PluginMarket",
		"version": "all"
	},
	{
		"count": 5452,
		"name": "search-this-singer",
		"version": "all"
	},
	{
		"count": 96183,
		"name": "light-dark-theme-switcher",
		"version": "all"
	},
	{
		"count": 2501,
		"name": "BGEnhanced-Extra",
		"version": "all"
	},
	{
		"count": 5326,
		"name": "Customize",
		"version": "all"
	},
	{
		"count": 32805,
		"name": "MikuPlugin",
		"version": "all"
	},
	{
		"count": 20696,
		"name": "Transmission",
		"version": "all"
	},
	{
		"count": 19434,
		"name": "ark-theme",
		"version": "all"
	},
	{
		"count": 17048,
		"name": "Unbounded",
		"version": "all"
	},
	{
		"count": 70202,
		"name": "FluentProgressBar",
		"version": "all"
	},
	{
		"count": 5768,
		"name": "PlaybackRate",
		"version": "all"
	},
	{
		"count": 6538,
		"name": "HideScrollbar",
		"version": "all"
	},
	{
		"count": 23537,
		"name": "ActionEnhancement",
		"version": "all"
	},
	{
		"count": 38233,
		"name": "crossfade-lfp",
		"version": "all"
	},
	{
		"count": 8165,
		"name": "CrashFix",
		"version": "all"
	},
	{
		"count": 13118,
		"name": "Microrange",
		"version": "all"
	},
	{
		"count": 6557,
		"name": "LiveSongPlayer",
		"version": "all"
	},
	{
		"count": 94575,
		"name": "BGEnhanced",
		"version": "all"
	},
	{
		"count": 7483,
		"name": "remove-tracking-attribute",
		"version": "all"
	},
	{
		"count": 7036,
		"name": "relive-theme",
		"version": "all"
	},
	{
		"count": 28682,
		"name": "What-is-the-cover-of-this-music",
		"version": "all"
	}
]