[
	{
		"count": 72239,
		"name": "list-scroll-fix",
		"version": "all"
	},
	{
		"count": 58930,
		"name": "RoundCornerNCM",
		"version": "all"
	},
	{
		"count": 3620,
		"name": "search-this-singer",
		"version": "all"
	},
	{
		"count": 3444,
		"name": "keyboard-seek",
		"version": "all"
	},
	{
		"count": 16870,
		"name": "crossfade-lfp",
		"version": "all"
	},
	{
		"count": 5661,
		"name": "Apple-Musiclike-lyrics-2-0-Beta",
		"version": "all"
	},
	{
		"count": 0,
		"name": "PluginMarket",
		"version": "all"
	},
	{
		"count": 59110,
		"name": "BGEnhanced",
		"version": "all"
	},
	{
		"count": 20515,
		"name": "SimpleAudioVisualizer",
		"version": "all"
	},
	{
		"count": 7920,
		"name": "play-with-bilibili",
		"version": "all"
	},
	{
		"count": 28629,
		"name": "libsonginfo",
		"version": "all"
	},
	{
		"count": 4107,
		"name": "CrashFix",
		"version": "all"
	},
	{
		"count": 48340,
		"name": "FluentProgressBar",
		"version": "all"
	},
	{
		"count": 17790,
		"name": "elaina-theme",
		"version": "all"
	},
	{
		"count": 36332,
		"name": "LibFrontendPlay",
		"version": "all"
	},
	{
		"count": 1829,
		"name": "RevivedUnblockInstaller",
		"version": "all"
	},
	{
		"count": 21440,
		"name": "RuLyrics",
		"version": "all"
	},
	{
		"count": 13326,
		"name": "Transmission",
		"version": "all"
	},
	{
		"count": 16942,
		"name": "ActionEnhancement",
		"version": "all"
	},
	{
		"count": 16434,
		"name": "ark-theme",
		"version": "all"
	},
	{
		"count": 59010,
		"name": "LibEAPIRequest",
		"version": "all"
	},
	{
		"count": 20943,
		"name": "VisualRecord",
		"version": "all"
	},
	{
		"count": 94348,
		"name": "RefinedNowPlaying",
		"version": "all"
	},
	{
		"count": 3492,
		"name": "search-on-osu",
		"version": "all"
	},
	{
		"count": 10593,
		"name": "FluentMusicCover",
		"version": "all"
	},
	{
		"count": 40049,
		"name": "StyleSnippet",
		"version": "all"
	},
	{
		"count": 0,
		"name": "MoreHooks",
		"version": "all"
	},
	{
		"count": 43910,
		"name": "Taskbar-Lyrics",
		"version": "all"
	},
	{
		"count": 22880,
		"name": "What-is-the-cover-of-this-music",
		"version": "all"
	},
	{
		"count": 58327,
		"name": "liblyric",
		"version": "all"
	},
	{
		"count": 157653,
		"name": "InfLink",
		"version": "all"
	},
	{
		"count": 76123,
		"name": "MaterialYouTheme",
		"version": "all"
	},
	{
		"count": 45473,
		"name": "light-dark-theme-switcher",
		"version": "all"
	},
	{
		"count": 58503,
		"name": "MoTheme",
		"version": "all"
	},
	{
		"count": 10811,
		"name": "Unbounded",
		"version": "all"
	},
	{
		"count": 4728,
		"name": "HideScrollbar",
		"version": "all"
	},
	{
		"count": 26664,
		"name": "TinyNCM",
		"version": "all"
	},
	{
		"count": 3502,
		"name": "Customize",
		"version": "all"
	},
	{
		"count": 4187,
		"name": "remove-tracking-attribute",
		"version": "all"
	},
	{
		"count": 0,
		"name": "UnblockCloudMusicInstaller",
		"version": "all"
	},
	{
		"count": 3547,
		"name": "PlaybackRate",
		"version": "all"
	},
	{
		"count": 8391,
		"name": "GPTTrans",
		"version": "all"
	},
	{
		"count": 14910,
		"name": "LyricBar",
		"version": "all"
	},
	{
		"count": 5381,
		"name": "relive-theme",
		"version": "all"
	},
	{
		"count": 21333,
		"name": "MikuPlugin",
		"version": "all"
	},
	{
		"count": 2594,
		"name": "RevivedSource",
		"version": "all"
	},
	{
		"count": 71308,
		"name": "StylesheetLoader",
		"version": "all"
	},
	{
		"count": 4962,
		"name": "LiveSongPlayer",
		"version": "all"
	},
	{
		"count": 3990,
		"name": "vocaloid-info",
		"version": "all"
	},
	{
		"count": 8277,
		"name": "Microrange",
		"version": "all"
	},
	{
		"count": 36257,
		"name": "Apple-Musiclike-lyrics",
		"version": "all"
	}
]