[
	{
		"count": 184337,
		"name": "StylesheetLoader",
		"version": "all"
	},
	{
		"count": 66553,
		"name": "Apple-Musiclike-lyrics",
		"version": "all"
	},
	{
		"count": 27427,
		"name": "libsonginfo",
		"version": "all"
	},
	{
		"count": 7954,
		"name": "DowngradeOK",
		"version": "all"
	},
	{
		"count": 50581,
		"name": "TinyNCM",
		"version": "all"
	},
	{
		"count": 18046,
		"name": "GPTTrans",
		"version": "all"
	},
	{
		"count": 227516,
		"name": "RefinedNowPlaying",
		"version": "all"
	},
	{
		"count": 45346,
		"name": "SimpleAudioVisualizer",
		"version": "all"
	},
	{
		"count": 18502,
		"name": "play-with-bilibili",
		"version": "all"
	},
	{
		"count": 5082,
		"name": "PiPWindow",
		"version": "all"
	},
	{
		"count": 42201,
		"name": "LyricBar",
		"version": "all"
	},
	{
		"count": 139446,
		"name": "LibEAPIRequest",
		"version": "all"
	},
	{
		"count": 103110,
		"name": "LibFrontendPlay",
		"version": "all"
	},
	{
		"count": 5408,
		"name": "vocaloid-info",
		"version": "all"
	},
	{
		"count": 65512,
		"name": "RuLyrics",
		"version": "all"
	},
	{
		"count": 2664,
		"name": "LyricBarBlur",
		"version": "all"
	},
	{
		"count": 191442,
		"name": "InfLink",
		"version": "all"
	},
	{
		"count": 29574,
		"name": "LogCleaner",
		"version": "all"
	},
	{
		"count": 1100,
		"name": "cpplyrics",
		"version": "all"
	},
	{
		"count": 91394,
		"name": "StyleSnippet",
		"version": "all"
	},
	{
		"count": 62811,
		"name": "Taskbar-Lyrics",
		"version": "all"
	},
	{
		"count": 0,
		"name": "MoreHooks",
		"version": "all"
	},
	{
		"count": 1539,
		"name": "artist-all-songs",
		"version": "all"
	},
	{
		"count": 163597,
		"name": "MoTheme",
		"version": "all"
	},
	{
		"count": 6778,
		"name": "Apple-Musiclike-lyrics-2-0-Beta",
		"version": "all"
	},
	{
		"count": 10603,
		"name": "keyboard-seek",
		"version": "all"
	},
	{
		"count": 117301,
		"name": "MaterialYouTheme",
		"version": "all"
	},
	{
		"count": 235983,
		"name": "list-scroll-fix",
		"version": "all"
	},
	{
		"count": 28315,
		"name": "elaina-theme",
		"version": "all"
	},
	{
		"count": 164591,
		"name": "RoundCornerNCM",
		"version": "all"
	},
	{
		"count": 7174,
		"name": "search-on-osu",
		"version": "all"
	},
	{
		"count": 132225,
		"name": "liblyric",
		"version": "all"
	},
	{
		"count": 21946,
		"name": "FluentMusicCover",
		"version": "all"
	},
	{
		"count": 7348,
		"name": "RevisedSecondaryWindows",
		"version": "all"
	},
	{
		"count": 1685,
		"name": "JapaneseFonts",
		"version": "all"
	},
	{
		"count": 25475,
		"name": "RevivedSource",
		"version": "all"
	},
	{
		"count": 3553,
		"name": "beat-saver",
		"version": "all"
	},
	{
		"count": 51143,
		"name": "VisualRecord",
		"version": "all"
	},
	{
		"count": 0,
		"name": "PluginMarket",
		"version": "all"
	},
	{
		"count": 8025,
		"name": "search-this-singer",
		"version": "all"
	},
	{
		"count": 165291,
		"name": "light-dark-theme-switcher",
		"version": "all"
	},
	{
		"count": 3202,
		"name": "ZoomNCM",
		"version": "all"
	},
	{
		"count": 8983,
		"name": "BGEnhanced-Extra",
		"version": "all"
	},
	{
		"count": 6928,
		"name": "Customize",
		"version": "all"
	},
	{
		"count": 46793,
		"name": "MikuPlugin",
		"version": "all"
	},
	{
		"count": 29600,
		"name": "Transmission",
		"version": "all"
	},
	{
		"count": 37886,
		"name": "ark-theme",
		"version": "all"
	},
	{
		"count": 24108,
		"name": "Unbounded",
		"version": "all"
	},
	{
		"count": 108732,
		"name": "FluentProgressBar",
		"version": "all"
	},
	{
		"count": 9581,
		"name": "PlaybackRate",
		"version": "all"
	},
	{
		"count": 9305,
		"name": "HideScrollbar",
		"version": "all"
	},
	{
		"count": 32338,
		"name": "ActionEnhancement",
		"version": "all"
	},
	{
		"count": 67880,
		"name": "crossfade-lfp",
		"version": "all"
	},
	{
		"count": 14872,
		"name": "CrashFix",
		"version": "all"
	},
	{
		"count": 19009,
		"name": "Microrange",
		"version": "all"
	},
	{
		"count": 8230,
		"name": "LiveSongPlayer",
		"version": "all"
	},
	{
		"count": 149033,
		"name": "BGEnhanced",
		"version": "all"
	},
	{
		"count": 14561,
		"name": "remove-tracking-attribute",
		"version": "all"
	},
	{
		"count": 12558,
		"name": "relive-theme",
		"version": "all"
	},
	{
		"count": 42408,
		"name": "What-is-the-cover-of-this-music",
		"version": "all"
	}
]