[
	{
		"count": 110274,
		"name": "list-scroll-fix",
		"version": "all"
	},
	{
		"count": 78053,
		"name": "RoundCornerNCM",
		"version": "all"
	},
	{
		"count": 4933,
		"name": "search-this-singer",
		"version": "all"
	},
	{
		"count": 4931,
		"name": "keyboard-seek",
		"version": "all"
	},
	{
		"count": 25818,
		"name": "crossfade-lfp",
		"version": "all"
	},
	{
		"count": 5661,
		"name": "Apple-Musiclike-lyrics-2-0-Beta",
		"version": "all"
	},
	{
		"count": 0,
		"name": "PluginMarket",
		"version": "all"
	},
	{
		"count": 85150,
		"name": "BGEnhanced",
		"version": "all"
	},
	{
		"count": 26316,
		"name": "SimpleAudioVisualizer",
		"version": "all"
	},
	{
		"count": 11290,
		"name": "play-with-bilibili",
		"version": "all"
	},
	{
		"count": 28672,
		"name": "libsonginfo",
		"version": "all"
	},
	{
		"count": 5620,
		"name": "CrashFix",
		"version": "all"
	},
	{
		"count": 62515,
		"name": "FluentProgressBar",
		"version": "all"
	},
	{
		"count": 28241,
		"name": "elaina-theme",
		"version": "all"
	},
	{
		"count": 49736,
		"name": "LibFrontendPlay",
		"version": "all"
	},
	{
		"count": 2949,
		"name": "RevivedUnblockInstaller",
		"version": "all"
	},
	{
		"count": 30233,
		"name": "RuLyrics",
		"version": "all"
	},
	{
		"count": 16755,
		"name": "Transmission",
		"version": "all"
	},
	{
		"count": 20636,
		"name": "ActionEnhancement",
		"version": "all"
	},
	{
		"count": 23168,
		"name": "ark-theme",
		"version": "all"
	},
	{
		"count": 77159,
		"name": "LibEAPIRequest",
		"version": "all"
	},
	{
		"count": 26993,
		"name": "VisualRecord",
		"version": "all"
	},
	{
		"count": 124401,
		"name": "RefinedNowPlaying",
		"version": "all"
	},
	{
		"count": 4428,
		"name": "search-on-osu",
		"version": "all"
	},
	{
		"count": 13483,
		"name": "FluentMusicCover",
		"version": "all"
	},
	{
		"count": 50849,
		"name": "StyleSnippet",
		"version": "all"
	},
	{
		"count": 0,
		"name": "MoreHooks",
		"version": "all"
	},
	{
		"count": 57999,
		"name": "Taskbar-Lyrics",
		"version": "all"
	},
	{
		"count": 28103,
		"name": "What-is-the-cover-of-this-music",
		"version": "all"
	},
	{
		"count": 75619,
		"name": "liblyric",
		"version": "all"
	},
	{
		"count": 198488,
		"name": "InfLink",
		"version": "all"
	},
	{
		"count": 98369,
		"name": "MaterialYouTheme",
		"version": "all"
	},
	{
		"count": 71479,
		"name": "light-dark-theme-switcher",
		"version": "all"
	},
	{
		"count": 82035,
		"name": "MoTheme",
		"version": "all"
	},
	{
		"count": 13948,
		"name": "Unbounded",
		"version": "all"
	},
	{
		"count": 5655,
		"name": "HideScrollbar",
		"version": "all"
	},
	{
		"count": 34677,
		"name": "TinyNCM",
		"version": "all"
	},
	{
		"count": 4408,
		"name": "Customize",
		"version": "all"
	},
	{
		"count": 5863,
		"name": "remove-tracking-attribute",
		"version": "all"
	},
	{
		"count": 0,
		"name": "UnblockCloudMusicInstaller",
		"version": "all"
	},
	{
		"count": 5093,
		"name": "PlaybackRate",
		"version": "all"
	},
	{
		"count": 11470,
		"name": "GPTTrans",
		"version": "all"
	},
	{
		"count": 20771,
		"name": "LyricBar",
		"version": "all"
	},
	{
		"count": 4102,
		"name": "BGEnhanced-Extra",
		"version": "all"
	},
	{
		"count": 7606,
		"name": "relive-theme",
		"version": "all"
	},
	{
		"count": 26674,
		"name": "MikuPlugin",
		"version": "all"
	},
	{
		"count": 9984,
		"name": "RevivedSource",
		"version": "all"
	},
	{
		"count": 96839,
		"name": "StylesheetLoader",
		"version": "all"
	},
	{
		"count": 5769,
		"name": "LiveSongPlayer",
		"version": "all"
	},
	{
		"count": 5402,
		"name": "vocaloid-info",
		"version": "all"
	},
	{
		"count": 10664,
		"name": "Microrange",
		"version": "all"
	},
	{
		"count": 45487,
		"name": "Apple-Musiclike-lyrics",
		"version": "all"
	}
]