[
	{
		"count": 118155,
		"name": "StylesheetLoader",
		"version": "all"
	},
	{
		"count": 43688,
		"name": "Apple-Musiclike-lyrics",
		"version": "all"
	},
	{
		"count": 27256,
		"name": "libsonginfo",
		"version": "all"
	},
	{
		"count": 32838,
		"name": "TinyNCM",
		"version": "all"
	},
	{
		"count": 12284,
		"name": "GPTTrans",
		"version": "all"
	},
	{
		"count": 112115,
		"name": "RefinedNowPlaying",
		"version": "all"
	},
	{
		"count": 31115,
		"name": "SimpleAudioVisualizer",
		"version": "all"
	},
	{
		"count": 12407,
		"name": "play-with-bilibili",
		"version": "all"
	},
	{
		"count": 23174,
		"name": "LyricBar",
		"version": "all"
	},
	{
		"count": 96010,
		"name": "LibEAPIRequest",
		"version": "all"
	},
	{
		"count": 64016,
		"name": "LibFrontendPlay",
		"version": "all"
	},
	{
		"count": 2273,
		"name": "vocaloid-info",
		"version": "all"
	},
	{
		"count": 40427,
		"name": "RuLyrics",
		"version": "all"
	},
	{
		"count": 137093,
		"name": "InfLink",
		"version": "all"
	},
	{
		"count": 7466,
		"name": "LogCleaner",
		"version": "all"
	},
	{
		"count": 61755,
		"name": "StyleSnippet",
		"version": "all"
	},
	{
		"count": 38489,
		"name": "Taskbar-Lyrics",
		"version": "all"
	},
	{
		"count": 0,
		"name": "MoreHooks",
		"version": "all"
	},
	{
		"count": 101579,
		"name": "MoTheme",
		"version": "all"
	},
	{
		"count": 6288,
		"name": "keyboard-seek",
		"version": "all"
	},
	{
		"count": 74957,
		"name": "MaterialYouTheme",
		"version": "all"
	},
	{
		"count": 150491,
		"name": "list-scroll-fix",
		"version": "all"
	},
	{
		"count": 13307,
		"name": "elaina-theme",
		"version": "all"
	},
	{
		"count": 102801,
		"name": "RoundCornerNCM",
		"version": "all"
	},
	{
		"count": 5425,
		"name": "search-on-osu",
		"version": "all"
	},
	{
		"count": 92376,
		"name": "liblyric",
		"version": "all"
	},
	{
		"count": 12480,
		"name": "FluentMusicCover",
		"version": "all"
	},
	{
		"count": 13396,
		"name": "RevivedSource",
		"version": "all"
	},
	{
		"count": 1068,
		"name": "beat-saver",
		"version": "all"
	},
	{
		"count": 34328,
		"name": "VisualRecord",
		"version": "all"
	},
	{
		"count": 0,
		"name": "PluginMarket",
		"version": "all"
	},
	{
		"count": 5538,
		"name": "search-this-singer",
		"version": "all"
	},
	{
		"count": 98695,
		"name": "light-dark-theme-switcher",
		"version": "all"
	},
	{
		"count": 2694,
		"name": "BGEnhanced-Extra",
		"version": "all"
	},
	{
		"count": 5402,
		"name": "Customize",
		"version": "all"
	},
	{
		"count": 33199,
		"name": "MikuPlugin",
		"version": "all"
	},
	{
		"count": 21186,
		"name": "Transmission",
		"version": "all"
	},
	{
		"count": 20178,
		"name": "ark-theme",
		"version": "all"
	},
	{
		"count": 17450,
		"name": "Unbounded",
		"version": "all"
	},
	{
		"count": 71696,
		"name": "FluentProgressBar",
		"version": "all"
	},
	{
		"count": 5861,
		"name": "PlaybackRate",
		"version": "all"
	},
	{
		"count": 6620,
		"name": "HideScrollbar",
		"version": "all"
	},
	{
		"count": 23821,
		"name": "ActionEnhancement",
		"version": "all"
	},
	{
		"count": 39236,
		"name": "crossfade-lfp",
		"version": "all"
	},
	{
		"count": 8336,
		"name": "CrashFix",
		"version": "all"
	},
	{
		"count": 13380,
		"name": "Microrange",
		"version": "all"
	},
	{
		"count": 6623,
		"name": "LiveSongPlayer",
		"version": "all"
	},
	{
		"count": 96066,
		"name": "BGEnhanced",
		"version": "all"
	},
	{
		"count": 7627,
		"name": "remove-tracking-attribute",
		"version": "all"
	},
	{
		"count": 7266,
		"name": "relive-theme",
		"version": "all"
	},
	{
		"count": 29071,
		"name": "What-is-the-cover-of-this-music",
		"version": "all"
	}
]