[
	{
		"count": 112392,
		"name": "StylesheetLoader",
		"version": "all"
	},
	{
		"count": 40859,
		"name": "Apple-Musiclike-lyrics",
		"version": "all"
	},
	{
		"count": 27247,
		"name": "libsonginfo",
		"version": "all"
	},
	{
		"count": 31600,
		"name": "TinyNCM",
		"version": "all"
	},
	{
		"count": 11730,
		"name": "GPTTrans",
		"version": "all"
	},
	{
		"count": 99091,
		"name": "RefinedNowPlaying",
		"version": "all"
	},
	{
		"count": 29836,
		"name": "SimpleAudioVisualizer",
		"version": "all"
	},
	{
		"count": 11875,
		"name": "play-with-bilibili",
		"version": "all"
	},
	{
		"count": 21667,
		"name": "LyricBar",
		"version": "all"
	},
	{
		"count": 91927,
		"name": "LibEAPIRequest",
		"version": "all"
	},
	{
		"count": 60484,
		"name": "LibFrontendPlay",
		"version": "all"
	},
	{
		"count": 1957,
		"name": "vocaloid-info",
		"version": "all"
	},
	{
		"count": 38010,
		"name": "RuLyrics",
		"version": "all"
	},
	{
		"count": 129998,
		"name": "InfLink",
		"version": "all"
	},
	{
		"count": 6043,
		"name": "LogCleaner",
		"version": "all"
	},
	{
		"count": 58688,
		"name": "StyleSnippet",
		"version": "all"
	},
	{
		"count": 36106,
		"name": "Taskbar-Lyrics",
		"version": "all"
	},
	{
		"count": 0,
		"name": "MoreHooks",
		"version": "all"
	},
	{
		"count": 96448,
		"name": "MoTheme",
		"version": "all"
	},
	{
		"count": 5982,
		"name": "keyboard-seek",
		"version": "all"
	},
	{
		"count": 70689,
		"name": "MaterialYouTheme",
		"version": "all"
	},
	{
		"count": 142722,
		"name": "list-scroll-fix",
		"version": "all"
	},
	{
		"count": 12128,
		"name": "elaina-theme",
		"version": "all"
	},
	{
		"count": 96990,
		"name": "RoundCornerNCM",
		"version": "all"
	},
	{
		"count": 5293,
		"name": "search-on-osu",
		"version": "all"
	},
	{
		"count": 88646,
		"name": "liblyric",
		"version": "all"
	},
	{
		"count": 11722,
		"name": "FluentMusicCover",
		"version": "all"
	},
	{
		"count": 12595,
		"name": "RevivedSource",
		"version": "all"
	},
	{
		"count": 785,
		"name": "beat-saver",
		"version": "all"
	},
	{
		"count": 32849,
		"name": "VisualRecord",
		"version": "all"
	},
	{
		"count": 0,
		"name": "PluginMarket",
		"version": "all"
	},
	{
		"count": 5321,
		"name": "search-this-singer",
		"version": "all"
	},
	{
		"count": 93010,
		"name": "light-dark-theme-switcher",
		"version": "all"
	},
	{
		"count": 2187,
		"name": "BGEnhanced-Extra",
		"version": "all"
	},
	{
		"count": 5243,
		"name": "Customize",
		"version": "all"
	},
	{
		"count": 32082,
		"name": "MikuPlugin",
		"version": "all"
	},
	{
		"count": 20082,
		"name": "Transmission",
		"version": "all"
	},
	{
		"count": 18440,
		"name": "ark-theme",
		"version": "all"
	},
	{
		"count": 16598,
		"name": "Unbounded",
		"version": "all"
	},
	{
		"count": 68222,
		"name": "FluentProgressBar",
		"version": "all"
	},
	{
		"count": 5587,
		"name": "PlaybackRate",
		"version": "all"
	},
	{
		"count": 6394,
		"name": "HideScrollbar",
		"version": "all"
	},
	{
		"count": 23038,
		"name": "ActionEnhancement",
		"version": "all"
	},
	{
		"count": 36826,
		"name": "crossfade-lfp",
		"version": "all"
	},
	{
		"count": 7879,
		"name": "CrashFix",
		"version": "all"
	},
	{
		"count": 12798,
		"name": "Microrange",
		"version": "all"
	},
	{
		"count": 6466,
		"name": "LiveSongPlayer",
		"version": "all"
	},
	{
		"count": 92259,
		"name": "BGEnhanced",
		"version": "all"
	},
	{
		"count": 7205,
		"name": "remove-tracking-attribute",
		"version": "all"
	},
	{
		"count": 6726,
		"name": "relive-theme",
		"version": "all"
	},
	{
		"count": 28066,
		"name": "What-is-the-cover-of-this-music",
		"version": "all"
	}
]