[
	{
		"count": 161871,
		"name": "StylesheetLoader",
		"version": "all"
	},
	{
		"count": 61286,
		"name": "Apple-Musiclike-lyrics",
		"version": "all"
	},
	{
		"count": 27368,
		"name": "libsonginfo",
		"version": "all"
	},
	{
		"count": 45776,
		"name": "TinyNCM",
		"version": "all"
	},
	{
		"count": 16503,
		"name": "GPTTrans",
		"version": "all"
	},
	{
		"count": 187322,
		"name": "RefinedNowPlaying",
		"version": "all"
	},
	{
		"count": 41407,
		"name": "SimpleAudioVisualizer",
		"version": "all"
	},
	{
		"count": 16958,
		"name": "play-with-bilibili",
		"version": "all"
	},
	{
		"count": 35866,
		"name": "LyricBar",
		"version": "all"
	},
	{
		"count": 125542,
		"name": "LibEAPIRequest",
		"version": "all"
	},
	{
		"count": 90883,
		"name": "LibFrontendPlay",
		"version": "all"
	},
	{
		"count": 4613,
		"name": "vocaloid-info",
		"version": "all"
	},
	{
		"count": 58735,
		"name": "RuLyrics",
		"version": "all"
	},
	{
		"count": 179216,
		"name": "InfLink",
		"version": "all"
	},
	{
		"count": 22205,
		"name": "LogCleaner",
		"version": "all"
	},
	{
		"count": 82817,
		"name": "StyleSnippet",
		"version": "all"
	},
	{
		"count": 56129,
		"name": "Taskbar-Lyrics",
		"version": "all"
	},
	{
		"count": 0,
		"name": "MoreHooks",
		"version": "all"
	},
	{
		"count": 142018,
		"name": "MoTheme",
		"version": "all"
	},
	{
		"count": 9329,
		"name": "keyboard-seek",
		"version": "all"
	},
	{
		"count": 105100,
		"name": "MaterialYouTheme",
		"version": "all"
	},
	{
		"count": 207831,
		"name": "list-scroll-fix",
		"version": "all"
	},
	{
		"count": 24436,
		"name": "elaina-theme",
		"version": "all"
	},
	{
		"count": 148601,
		"name": "RoundCornerNCM",
		"version": "all"
	},
	{
		"count": 6719,
		"name": "search-on-osu",
		"version": "all"
	},
	{
		"count": 119357,
		"name": "liblyric",
		"version": "all"
	},
	{
		"count": 19038,
		"name": "FluentMusicCover",
		"version": "all"
	},
	{
		"count": 21720,
		"name": "RevivedSource",
		"version": "all"
	},
	{
		"count": 2888,
		"name": "beat-saver",
		"version": "all"
	},
	{
		"count": 46162,
		"name": "VisualRecord",
		"version": "all"
	},
	{
		"count": 0,
		"name": "PluginMarket",
		"version": "all"
	},
	{
		"count": 7379,
		"name": "search-this-singer",
		"version": "all"
	},
	{
		"count": 142526,
		"name": "light-dark-theme-switcher",
		"version": "all"
	},
	{
		"count": 7211,
		"name": "BGEnhanced-Extra",
		"version": "all"
	},
	{
		"count": 6503,
		"name": "Customize",
		"version": "all"
	},
	{
		"count": 42888,
		"name": "MikuPlugin",
		"version": "all"
	},
	{
		"count": 27718,
		"name": "Transmission",
		"version": "all"
	},
	{
		"count": 32734,
		"name": "ark-theme",
		"version": "all"
	},
	{
		"count": 22647,
		"name": "Unbounded",
		"version": "all"
	},
	{
		"count": 97878,
		"name": "FluentProgressBar",
		"version": "all"
	},
	{
		"count": 8534,
		"name": "PlaybackRate",
		"version": "all"
	},
	{
		"count": 8531,
		"name": "HideScrollbar",
		"version": "all"
	},
	{
		"count": 30393,
		"name": "ActionEnhancement",
		"version": "all"
	},
	{
		"count": 58263,
		"name": "crossfade-lfp",
		"version": "all"
	},
	{
		"count": 12767,
		"name": "CrashFix",
		"version": "all"
	},
	{
		"count": 17512,
		"name": "Microrange",
		"version": "all"
	},
	{
		"count": 7781,
		"name": "LiveSongPlayer",
		"version": "all"
	},
	{
		"count": 129414,
		"name": "BGEnhanced",
		"version": "all"
	},
	{
		"count": 12803,
		"name": "remove-tracking-attribute",
		"version": "all"
	},
	{
		"count": 11069,
		"name": "relive-theme",
		"version": "all"
	},
	{
		"count": 38193,
		"name": "What-is-the-cover-of-this-music",
		"version": "all"
	}
]