[
	{
		"count": 103453,
		"name": "StylesheetLoader",
		"version": "all"
	},
	{
		"count": 36814,
		"name": "Apple-Musiclike-lyrics",
		"version": "all"
	},
	{
		"count": 27229,
		"name": "libsonginfo",
		"version": "all"
	},
	{
		"count": 29508,
		"name": "TinyNCM",
		"version": "all"
	},
	{
		"count": 10879,
		"name": "GPTTrans",
		"version": "all"
	},
	{
		"count": 86951,
		"name": "RefinedNowPlaying",
		"version": "all"
	},
	{
		"count": 27812,
		"name": "SimpleAudioVisualizer",
		"version": "all"
	},
	{
		"count": 11020,
		"name": "play-with-bilibili",
		"version": "all"
	},
	{
		"count": 19292,
		"name": "LyricBar",
		"version": "all"
	},
	{
		"count": 85705,
		"name": "LibEAPIRequest",
		"version": "all"
	},
	{
		"count": 54747,
		"name": "LibFrontendPlay",
		"version": "all"
	},
	{
		"count": 1477,
		"name": "vocaloid-info",
		"version": "all"
	},
	{
		"count": 34287,
		"name": "RuLyrics",
		"version": "all"
	},
	{
		"count": 117440,
		"name": "InfLink",
		"version": "all"
	},
	{
		"count": 3877,
		"name": "LogCleaner",
		"version": "all"
	},
	{
		"count": 54106,
		"name": "StyleSnippet",
		"version": "all"
	},
	{
		"count": 32526,
		"name": "Taskbar-Lyrics",
		"version": "all"
	},
	{
		"count": 0,
		"name": "MoreHooks",
		"version": "all"
	},
	{
		"count": 88370,
		"name": "MoTheme",
		"version": "all"
	},
	{
		"count": 5529,
		"name": "keyboard-seek",
		"version": "all"
	},
	{
		"count": 64141,
		"name": "MaterialYouTheme",
		"version": "all"
	},
	{
		"count": 130552,
		"name": "list-scroll-fix",
		"version": "all"
	},
	{
		"count": 10067,
		"name": "elaina-theme",
		"version": "all"
	},
	{
		"count": 89068,
		"name": "RoundCornerNCM",
		"version": "all"
	},
	{
		"count": 5063,
		"name": "search-on-osu",
		"version": "all"
	},
	{
		"count": 82949,
		"name": "liblyric",
		"version": "all"
	},
	{
		"count": 10618,
		"name": "FluentMusicCover",
		"version": "all"
	},
	{
		"count": 11072,
		"name": "RevivedSource",
		"version": "all"
	},
	{
		"count": 309,
		"name": "beat-saver",
		"version": "all"
	},
	{
		"count": 30751,
		"name": "VisualRecord",
		"version": "all"
	},
	{
		"count": 0,
		"name": "PluginMarket",
		"version": "all"
	},
	{
		"count": 4998,
		"name": "search-this-singer",
		"version": "all"
	},
	{
		"count": 84229,
		"name": "light-dark-theme-switcher",
		"version": "all"
	},
	{
		"count": 1314,
		"name": "BGEnhanced-Extra",
		"version": "all"
	},
	{
		"count": 4985,
		"name": "Customize",
		"version": "all"
	},
	{
		"count": 30237,
		"name": "MikuPlugin",
		"version": "all"
	},
	{
		"count": 18583,
		"name": "Transmission",
		"version": "all"
	},
	{
		"count": 15893,
		"name": "ark-theme",
		"version": "all"
	},
	{
		"count": 15431,
		"name": "Unbounded",
		"version": "all"
	},
	{
		"count": 62984,
		"name": "FluentProgressBar",
		"version": "all"
	},
	{
		"count": 5126,
		"name": "PlaybackRate",
		"version": "all"
	},
	{
		"count": 6080,
		"name": "HideScrollbar",
		"version": "all"
	},
	{
		"count": 21437,
		"name": "ActionEnhancement",
		"version": "all"
	},
	{
		"count": 32935,
		"name": "crossfade-lfp",
		"version": "all"
	},
	{
		"count": 7102,
		"name": "CrashFix",
		"version": "all"
	},
	{
		"count": 11995,
		"name": "Microrange",
		"version": "all"
	},
	{
		"count": 6205,
		"name": "LiveSongPlayer",
		"version": "all"
	},
	{
		"count": 85937,
		"name": "BGEnhanced",
		"version": "all"
	},
	{
		"count": 6469,
		"name": "remove-tracking-attribute",
		"version": "all"
	},
	{
		"count": 5888,
		"name": "relive-theme",
		"version": "all"
	},
	{
		"count": 26412,
		"name": "What-is-the-cover-of-this-music",
		"version": "all"
	}
]